pysorteddict.cpython-313-darwin.so
pysorteddict-0.13.0.dist-info/RECORD
pysorteddict-0.13.0.dist-info/WHEEL
pysorteddict-0.13.0.dist-info/METADATA
