Metadata-Version: 2.4
Name: pysorteddict
Version: 0.13.0
Summary: Python dictionary in which the keys are always in ascending order
Author: Vishal Pankaj Chandratreya
License-Expression: AGPL-3.0-or-later
Classifier: Development Status :: 4 - Beta
Classifier: Intended Audience :: Developers
Classifier: Operating System :: MacOS
Classifier: Operating System :: Microsoft :: Windows
Classifier: Operating System :: POSIX
Classifier: Operating System :: Unix
Classifier: Programming Language :: Python :: 3
Classifier: Programming Language :: Python :: 3 :: Only
Classifier: Programming Language :: Python :: 3.10
Classifier: Programming Language :: Python :: 3.11
Classifier: Programming Language :: Python :: 3.12
Classifier: Programming Language :: Python :: 3.13
Classifier: Programming Language :: Python :: 3.14
Classifier: Programming Language :: Python :: Implementation :: CPython
Classifier: Programming Language :: Python :: Implementation :: PyPy
Project-URL: Homepage, https://tfpf.github.io/pysorteddict/
Project-URL: Documentation, https://tfpf.github.io/pysorteddict/documentation.html
Project-URL: Repository, https://github.com/tfpf/pysorteddict
Project-URL: Changelog, https://tfpf.github.io/pysorteddict/changelog.html
Requires-Python: >=3.10
Provides-Extra: cov
Requires-Dist: gcovr; extra == "cov"
Requires-Dist: pytest-xdist; extra == "cov"
